[
    {
        "author": [
            "Hiroki Kogami",
            "Qi An",
            "Ningjia Yang",
            "Ruoxi Wang",
            "Kazunori Yoshida",
            "Hiroyuki Hamada",
            "Hiroshi Yamakawa",
            "Yusuke Tamura",
            "Shingo Shimoda",
            "Hiroshi Yamasaki",
            "Moeka Sonoo",
            "Fady Alnajjar",
            "Noriaki Hattori",
            "Koji Takahashi",
            "Takanori Fujii",
            "Hironori Otomune",
            "Ichiro Miyai",
            "Atsushi Yamashita",
            "Hajime Asama"
        ],
        "title": "Analysis of Muscle Synergy and Kinematics in Sit-to-Stand Motion of Hemiplegic Patients in Subacute Period",
        "journal": "Advanced Robotics",
        "vol": "",
        "no": "",
        "page": "",
        "url": "",
        "year": "2021 (accepted)"
    },

    {
        "author": [
            "Kei Aoyagi",
            "Wen Wen",
            "Qi An",
            "Shunsuke Hamasaki",
            "Hiroshi Yamakawa",
            "Yusuke Tamura",
            "Atsushi Yamashita",
            "Hajime Asama"
        ],
        "title": "Modified Sensory Feedback Enhances the Sense of Agency during Continuous Body Movements in Virtual Reality",
        "journal": "Scientific Reports",
        "vol": "11",
        "no": "2553",
        "page": "pp.1-10",
        "url": "https://doi.org/10.1038/s41598-021-82154-y",
        "year": "2021"
    }
]